pheval_talos/__init__.py
pheval_talos/cli.py
pheval_talos/main.py
pheval_talos/post_process/__init__.py
pheval_talos/prepare/__init__.py
pheval_talos/prepare/create_cohort.py
pheval_talos/prepare/edit_next_flow_configs.py
pheval_talos/prepare/prepare.py
pheval_talos/run/__init__.py
pheval_talos/run/run.py
pheval_talos/runner.py
pheval_talos/tool_specific_configuration_options.py
pheval_talos-0.1.0.dist-info/LICENSE
pheval_talos-0.1.0.dist-info/METADATA
pheval_talos-0.1.0.dist-info/WHEEL
pheval_talos-0.1.0.dist-info/entry_points.txt
pheval_talos-0.1.0.dist-info/RECORD
