Metadata-Version: 2.3
Name: pheval_talos
Version: 0.1.0
Summary: pheval_talos
License: MIT
Author: Yasemin Bridges
Author-email: y.bridges@qmul.ac.uk
Requires-Python: >=3.10,<4.0
Classifier: License :: OSI Approved :: MIT License
Classifier: Programming Language :: Python :: 3
Classifier: Programming Language :: Python :: 3.10
Classifier: Programming Language :: Python :: 3.11
Classifier: Programming Language :: Python :: 3.12
Classifier: Programming Language :: Python :: 3.13
Requires-Dist: click
Requires-Dist: importlib-metadata (>=8.2.0)
Requires-Dist: pheval (>=0.6.0,<0.7.0)
